antares/__init__.py
antares/version.py
antares/ansatze/__init__.py
antares/ansatze/eigenbasis.py
antares/ansatze/fitter.py
antares/core/__init__.py
antares/core/bh_patch.py
antares/core/bh_unknown.py
antares/core/my_warnings.py
antares/core/numerical_methods.py
antares/core/se_unknown.py
antares/core/settings.py
antares/core/tools.py
antares/core/unknown.py
antares/partial_fractioning/__init__.py
antares/scalings/__init__.py
antares/scalings/pair.py
antares/scalings/single.py
antares/scripts/SpinorLatexCompiler.py
antares/scripts/__init__.py
antares/terms/__init__.py
antares/terms/lterms.py
antares/terms/term.py
antares/terms/terms.py
antares/terms/terms_numerator_fit.py
antares/topologies/__init__.py
antares/topologies/topology.py
antares_hep-0.7.0.dist-info/LICENSE.txt
antares_hep-0.7.0.dist-info/METADATA
antares_hep-0.7.0.dist-info/WHEEL
antares_hep-0.7.0.dist-info/entry_points.txt
antares_hep-0.7.0.dist-info/top_level.txt
antares_hep-0.7.0.dist-info/RECORD
