Metadata-Version: 2.1
Name: antares-hep
Version: 0.7.0
Summary: Automated Numerical To Analytical REconstruction Software
Home-page: https://github.com/GDeLaurentis/antares
Download-URL: https://github.com/GDeLaurentis/antares/archive/v0.7.0.tar.gz
Author: Giuseppe De Laurentis, Daniel Maitre
Author-email: g.dl@hotmail.it
License: GNU General Public License v3.0
Project-URL: Documentation, https://gdelaurentis.github.io/antares/
Project-URL: Issues, https://github.com/GDeLaurentis/antares/issues
Keywords: Analytic Reconstruction,Spinor Helicity,Scattering Amplitudes,QFT
Classifier: Development Status :: 3 - Alpha
Classifier: Intended Audience :: Science/Research
Classifier: Topic :: Scientific/Engineering :: Physics
Classifier: License :: OSI Approved :: GNU General Public License v3 (GPLv3)
Classifier: Programming Language :: Python :: 3.9
Classifier: Programming Language :: Python :: 3.10
Classifier: Programming Language :: Python :: 3.11
Classifier: Programming Language :: Python :: 3.12
Classifier: Programming Language :: Python :: 3.13
License-File: LICENSE.txt
Requires-Dist: lips >=0.5.0
Requires-Dist: multiset
Requires-Dist: pandas
Requires-Dist: pyadic >=0.2.4
Requires-Dist: pyyaml
Requires-Dist: syngular >=0.5.0
